MFDFA/MFDFA.py
MFDFA/__init__.py
MFDFA/emddetrender.py
MFDFA/fgn.py
MFDFA/singspect.py
MFDFA-0.4.3.dist-info/LICENSE
MFDFA-0.4.3.dist-info/METADATA
MFDFA-0.4.3.dist-info/WHEEL
MFDFA-0.4.3.dist-info/top_level.txt
MFDFA-0.4.3.dist-info/RECORD
