Metadata-Version: 2.1
Name: MFDFA
Version: 0.4.3
Summary: Multifractal Detrended Fluctuation Analysis in Python
Home-page: https://github.com/LRydin/MFDFA
Author: Leonardo Rydin Gorjao
Author-email: leonardo.rydin@gmail.com
License: MIT License
Classifier: Programming Language :: Python :: 3
Classifier: License :: OSI Approved :: MIT License
Classifier: Operating System :: OS Independent
Requires-Python: >=3.6
License-File: LICENSE
Requires-Dist: numpy
Provides-Extra: emd-signal
Requires-Dist: EMD-signal ; extra == 'emd-signal'
Provides-Extra: matplotlib
Requires-Dist: matplotlib ; extra == 'matplotlib'
